predeval/__init__.py
predeval/categorical.py
predeval/continuous.py
predeval/parent.py
predeval/utilities.py
predeval-0.0.10.dist-info/AUTHORS.rst
predeval-0.0.10.dist-info/LICENSE
predeval-0.0.10.dist-info/METADATA
predeval-0.0.10.dist-info/WHEEL
predeval-0.0.10.dist-info/top_level.txt
predeval-0.0.10.dist-info/RECORD
