Metadata-Version: 2.1
Name: predeval
Version: 0.0.10
Summary: Identify changes in model outputs at prediction time.
Home-page: https://github.com/dvatterott/predeval
Author: Dan Vatterott
Author-email: dvatterott@gmail.com
License: MIT license
Keywords: predeval
Platform: UNKNOWN
Classifier: Development Status :: 2 - Pre-Alpha
Classifier: Intended Audience :: Developers
Classifier: Intended Audience :: Science/Research
Classifier: License :: OSI Approved :: MIT License
Classifier: Natural Language :: English
Classifier: Programming Language :: Python :: 3
Classifier: Programming Language :: Python :: 3.5
Classifier: Programming Language :: Python :: 3.6
Classifier: Programming Language :: Python :: 3.7
Classifier: Topic :: Software Development :: Libraries
Classifier: Topic :: Software Development :: Libraries :: Python Modules
Requires-Dist: numpy (>=1.17.0)
Requires-Dist: scipy (>=1.0.0)
Requires-Dist: joblib (>=0.9.2)
Requires-Dist: cloudpickle
